[
    {
        "nama" : "Bombay",
        "harga" : 3000,
        "toko" : "Rosa olshop",
        "tipe" : "/pcs",
        "kuantitas" : 5
    },
    {
        "nama" : "jagung",
        "harga" : 5000,
        "toko" : "Rosa olshop", 
        "tipe" : "/pcs",
        "kuantitas" : 30
    },
    {
        "nama" : "beras",
        "harga" : 10000,
        "toko" : "Rosa olshop", 
        "tipe" : "/kg",
        "kuantitas" : 10
    },
    {
        "nama" : "terong",
        "harga" : 5000,
        "toko" : "Rosa olshop", 
        "tipe" : "/iket",
        "kuantitas" : 4
    },
    {
        "nama" : "semangka",
        "harga" : 8000,
        "toko" : "Rosa olshop", 
        "tipe" : "/kg",
        "kuantitas" : 3
    }
]